{
  "generator-jhipster": {
    "applicationIndex": 1,
    "applicationType": "microservice",
    "authenticationType": "oauth2",
    "baseName": "blog",
    "buildTool": "gradle",
    "cacheProvider": "no",
    "clientFramework": "no",
    "clientPackageManager": "npm",
    "creationTimestamp": 1677564101356,
    "databaseType": "neo4j",
    "devDatabaseType": "neo4j",
    "dtoSuffix": "DTO",
    "enableGradleEnterprise": false,
    "enableHibernateCache": false,
    "enableSwaggerCodegen": false,
    "enableTranslation": true,
    "entities": ["Blog", "Post", "Tag"],
    "entitySuffix": "",
    "gatewayServerPort": 8080,
    "gradleEnterpriseHost": "",
    "jhiPrefix": "jhi",
    "jhipsterVersion": "7.9.3",
    "jwtSecretKey": "ZTgxNmE3NmNmY2IzNmQ3MWUyMGNjOTU0MDBhYmYwNGVjNTNjNDBmOTE0ZDNkYTNkNmIxZDNiOGQwNmNjNDY3NDI2ZDc5ZTQ0OTU1MmQ2NTY2ZjcwYjAxODQxMmNlYWFjMGU4OTA5YmY4MTUwNjFlNTU4MjcwZjY0MDFhMmE5NjY=",
    "languages": ["en"],
    "lastLiquibaseTimestamp": 1677564281000,
    "messageBroker": "no",
    "monorepository": true,
    "nativeLanguage": "en",
    "packageFolder": "com/okta/developer/blog",
    "packageName": "com.okta.developer.blog",
    "pages": [],
    "prodDatabaseType": "neo4j",
    "reactive": true,
    "searchEngine": "no",
    "serverPort": "8081",
    "serviceDiscoveryType": "eureka",
    "skipCheckLengthOfIdentifier": false,
    "skipClient": true,
    "skipCommitHook": true,
    "skipFakeData": false,
    "skipUserManagement": true,
    "testFrameworks": [],
    "websocket": "no",
    "withAdminUi": false
  }
}
